xcompact3d_toolbox/__init__.py
xcompact3d_toolbox/_version.py
xcompact3d_toolbox/array.py
xcompact3d_toolbox/derive.py
xcompact3d_toolbox/genepsi.py
xcompact3d_toolbox/gui.py
xcompact3d_toolbox/io.py
xcompact3d_toolbox/mesh.py
xcompact3d_toolbox/param.py
xcompact3d_toolbox/parameters.py
xcompact3d_toolbox/py.typed
xcompact3d_toolbox/sandbox.py
xcompact3d_toolbox/tutorial.py
xcompact3d_toolbox-1.3.3.dist-info/METADATA
xcompact3d_toolbox-1.3.3.dist-info/WHEEL
xcompact3d_toolbox-1.3.3.dist-info/licenses/LICENSE
xcompact3d_toolbox-1.3.3.dist-info/RECORD
