Metadata-Version: 2.4
Name: xcompact3d_toolbox
Version: 1.3.3
Summary: A set of tools for pre and postprocessing prepared for the high-order Navier-Stokes solver XCompact3d
Project-URL: Repository, https://github.com/fschuch/xcompact3d_toolbox
Project-URL: Changelog, https://docs.fschuch.com/xcompact3d_toolbox/references/what-is-new.html
Project-URL: Documentation, https://docs.fschuch.com/xcompact3d_toolbox
Project-URL: Issues, https://github.com/fschuch/xcompact3d_toolbox/issues
Author-email: "Felipe N. Schuch" <me@fschuch.com>
License-File: LICENSE
Classifier: Development Status :: 5 - Production/Stable
Classifier: Intended Audience :: Science/Research
Classifier: License :: OSI Approved :: GNU General Public License v3 (GPLv3)
Classifier: Programming Language :: Python
Classifier: Programming Language :: Python :: 3.9
Classifier: Programming Language :: Python :: 3.10
Classifier: Programming Language :: Python :: 3.11
Classifier: Programming Language :: Python :: 3.12
Classifier: Programming Language :: Python :: 3.13
Classifier: Topic :: Scientific/Engineering
Requires-Python: >=3.9
Requires-Dist: dask[complete]>=2024.8
Requires-Dist: deprecated>=1.2
Requires-Dist: ipywidgets>=8.1
Requires-Dist: loguru>=0.7
Requires-Dist: netcdf4>=1.7
Requires-Dist: numba>=0.60
Requires-Dist: numpy-stl>=3.2
Requires-Dist: numpy>=2.0
Requires-Dist: pandas>=2.2
Requires-Dist: scipy>=1.13
Requires-Dist: tqdm>=4.67
Requires-Dist: traitlets>=5.14
Requires-Dist: xarray>=2024.7
Provides-Extra: docs
Requires-Dist: docutils==0.21.2; extra == 'docs'
Requires-Dist: ipykernel==6.29.5; extra == 'docs'
Requires-Dist: jupyter-book==1.0.4.post1; extra == 'docs'
Requires-Dist: nbsphinx==0.9.7; extra == 'docs'
Requires-Dist: pooch==1.8.2; extra == 'docs'
Requires-Dist: sphinx-autobuild==2024.10.3; extra == 'docs'
Requires-Dist: sphinx-github-changelog==1.7.1; extra == 'docs'
Requires-Dist: sphinx==7.4.7; extra == 'docs'
Provides-Extra: tests
Requires-Dist: coverage[toml]>=7.5.3; extra == 'tests'
Requires-Dist: hypothesis>=6.103.1; extra == 'tests'
Requires-Dist: pre-commit>=3.5.0; extra == 'tests'
Requires-Dist: pytest-cov>=5.0.0; extra == 'tests'
Requires-Dist: pytest>=8.2.2; extra == 'tests'
Provides-Extra: tests-extra
Requires-Dist: pytest-randomly==3.16.0; extra == 'tests-extra'
Requires-Dist: pytest-rerunfailures==15.1; extra == 'tests-extra'
Requires-Dist: pytest-xdist==3.8.0; extra == 'tests-extra'
Provides-Extra: visu
Requires-Dist: bokeh>=2.3; extra == 'visu'
Requires-Dist: datashader>=0.13; extra == 'visu'
Requires-Dist: holoviews>=1.14; extra == 'visu'
Requires-Dist: hvplot>=0.7; extra == 'visu'
Requires-Dist: matplotlib>=3.2; extra == 'visu'
Requires-Dist: panel>=0.12; extra == 'visu'
